buddymojoAPI/BuddyMojoAPI.py
buddymojoAPI/__init__.py
buddymojoAPI/__main__.py
buddymojoAPI-1.0.10.dist-info/LICENSE
buddymojoAPI-1.0.10.dist-info/METADATA
buddymojoAPI-1.0.10.dist-info/WHEEL
buddymojoAPI-1.0.10.dist-info/top_level.txt
buddymojoAPI-1.0.10.dist-info/RECORD
