Metadata-Version: 2.1
Name: buddymojoAPI
Version: 1.0.10
Summary: An API of cn.buddymojo.com
Home-page: https://github.com/jasonjustin/BuddymojoAPI
Author: Jelly Hsu
Author-email: zxc3.zxc46@gmail.com
License: UNKNOWN
Platform: UNKNOWN
Classifier: Programming Language :: Python :: 3
Classifier: License :: OSI Approved :: MIT License
Classifier: Operating System :: OS Independent
Requires-Python: >=3.6
Requires-Dist: requests
Requires-Dist: argparse
